dumpmyrepos/__init__.py
dumpmyrepos/cli.py
dumpmyrepos/command.py
dumpmyrepos/config.py
dumpmyrepos/config.yml
dumpmyrepos/services/__init__.py
dumpmyrepos/services/bitbucket.py
dumpmyrepos/services/factory.py
dumpmyrepos/services/git.py
dumpmyrepos/services/github.py
dumpmyrepos/services/gitlab.py
dumpmyrepos-0.1.dist-info/DESCRIPTION.rst
dumpmyrepos-0.1.dist-info/entry_points.txt
dumpmyrepos-0.1.dist-info/METADATA
dumpmyrepos-0.1.dist-info/metadata.json
dumpmyrepos-0.1.dist-info/RECORD
dumpmyrepos-0.1.dist-info/top_level.txt
dumpmyrepos-0.1.dist-info/WHEEL
